mariadb_kernel/__init__.py
mariadb_kernel/__main__.py
mariadb_kernel/_version.py
mariadb_kernel/client_config.py
mariadb_kernel/code_parser.py
mariadb_kernel/install.py
mariadb_kernel/kernel.py
mariadb_kernel/mariadb_client.py
mariadb_kernel/mariadb_server.py
mariadb_kernel/code_completion/__init__.py
mariadb_kernel/code_completion/autocompleter.py
mariadb_kernel/code_completion/completion_engine.py
mariadb_kernel/code_completion/introspector.py
mariadb_kernel/code_completion/sql_analyze.py
mariadb_kernel/code_completion/sql_fetch.py
mariadb_kernel/maria_magics/__init__.py
mariadb_kernel/maria_magics/bar.py
mariadb_kernel/maria_magics/cell_magic.py
mariadb_kernel/maria_magics/delimiter.py
mariadb_kernel/maria_magics/df.py
mariadb_kernel/maria_magics/help.py
mariadb_kernel/maria_magics/line.py
mariadb_kernel/maria_magics/line_magic.py
mariadb_kernel/maria_magics/load.py
mariadb_kernel/maria_magics/lsmagic.py
mariadb_kernel/maria_magics/magic_factory.py
mariadb_kernel/maria_magics/maria_magic.py
mariadb_kernel/maria_magics/pie.py
mariadb_kernel/maria_magics/supported_magics.py
mariadb_kernel/tests/__init__.py
mariadb_kernel/tests/conftest.py
mariadb_kernel/tests/test_autocompleter.py
mariadb_kernel/tests/test_clientconfig.py
mariadb_kernel/tests/test_codeparser.py
mariadb_kernel/tests/test_introspector.py
mariadb_kernel/tests/test_magic_linemagic.py
mariadb_kernel/tests/test_magicfactory.py
mariadb_kernel/tests/test_magics.py
mariadb_kernel/tests/test_mariadbclient.py
mariadb_kernel/tests/test_mariadbkernel.py
mariadb_kernel/tests/test_mariadbserver.py
mariadb_kernel/tests/test_sql_fetch.py
mariadb_kernel-0.2.0.dist-info/LICENSE
mariadb_kernel-0.2.0.dist-info/METADATA
mariadb_kernel-0.2.0.dist-info/WHEEL
mariadb_kernel-0.2.0.dist-info/top_level.txt
mariadb_kernel-0.2.0.dist-info/RECORD
