Metadata-Version: 2.1
Name: mariadb-kernel
Version: 0.2.0
Summary: A simple MariaDB Jupyter kernel
Home-page: https://github.com/MariaDB/mariadb_kernel
Author: MariaDB Foundation
Author-email: foundation@mariadb.org
License: UNKNOWN
Platform: UNKNOWN
Classifier: License :: OSI Approved :: BSD License
Classifier: Programming Language :: Python :: 3
Requires-Python: >=3.5
License-File: LICENSE
Requires-Dist: pandas
Requires-Dist: json2html
Requires-Dist: matplotlib
Requires-Dist: lxml
Requires-Dist: setuptools
Requires-Dist: setuptools-scm
Requires-Dist: ipykernel
Requires-Dist: beautifulsoup4
Requires-Dist: mycli
